[
    {
    "task_label": "HomeWork",
    "is_completed": false,
    "date": "2024-01-14",
    "time":"12:22"
    
    },
    {
        "task_label": "Gym",
        "is_completed": false,
        "date": "2024-01-15",
        "time":"12:22"
    },
    {
        "task_label": "Office",
        "is_completed": false,
        "date": "2024-01-14",
        "time":"12:22"
    },
    {
        "task_label": "Study",
        "is_completed": false,
        "date": "2024-01-15",
        "time": "11:22"
    },
    {
        "task_label": "Yoga",
        "is_completed": false,
        "date": "2024-01-17",
        "time": "11:22"
    },
    {
        "task_label": "Homework",
        "is_completed": false,
        "date": "2024-01-20",
        "time": "11:22"
    },
    {
        "task_label": "Doctor",
        "is_completed": false,
        "date": "2024-01-30",
        "time": "11:22"
    }
   
]
